{
  "FOR CONTRACTORS & SUPPLIERS ONLY FOR PAYMENT FOR WORK OR SUPPLIES ACTUALLY MEASURED": null,
  "Bill Number": "First",
  "Running or Final": "Final",
  "Cash Book Voucher No. and Date": null,
  "Name of Contractor or supplier": "M/s. Shree Krishna Builders Jaipur",
  "Name of Work ;-": "Plumbing Installation and MTC work at Govt. Nehru hostel Mansarovar, Sanganer, Jaipur",
  "Serial No. of this bill": "First & Final Bill",
  "No. and date of the last bill-": "Not Applicable",
  "Reference to work order or Agreement": "0511 Dt. 05-11-2023",
  "Agreement No.": "48/2024-25",
  "WORK ORDER AMOUNT RS.": 87588,
  "Date of written order to commence work": "2024-11-05 00:00:00",
  "St. date of Start": "2024-11-12 00:00:00",
  "St. date of completion": "2025-08-09 00:00:00",
  "Date of actual completion of work": "2025-08-14 00:00:00",
  "Date of measurement": "2025-09-15 00:00:00",
  "TENDER PREMIUM %": 5.11,
  "Premium Type": "Above",
  "Amount Paid Vide Last Bill": 0
}